xontrib_dotdot/main.py
xontrib_dotdot-0.1.0.dist-info/LICENSE
xontrib_dotdot-0.1.0.dist-info/METADATA
xontrib_dotdot-0.1.0.dist-info/WHEEL
xontrib_dotdot-0.1.0.dist-info/entry_points.txt
xontrib_dotdot-0.1.0.dist-info/top_level.txt
xontrib_dotdot-0.1.0.dist-info/RECORD
