Metadata-Version: 2.1
Name: xontrib-dotdot
Version: 0.1.0
Summary: Better aliases['..'] = 'cd ..'
Author-email: Konstantin Schukraft <dotdot@schukraft.org>
License: Copyright (c) 2024, Konstantin Schukraft
Project-URL: Homepage, https://github.com/yggdr/xontrib-dotdot
Project-URL: Documentation, https://github.com/yggdr/xontrib-dotdot/blob/master/README.md
Project-URL: Code, https://github.com/yggdr/xontrib-dotdot
Project-URL: Issue tracker, https://github.com/yggdr/xontrib-dotdot/issues
Platform: any
Classifier: Programming Language :: Python :: 3
Classifier: License :: OSI Approved :: ISC License (ISCL)
Classifier: Operating System :: OS Independent
Classifier: Topic :: System :: Shells
Classifier: Topic :: System :: System Shells
Classifier: Topic :: Terminals
Requires-Python: >=3.8
License-File: LICENSE
Requires-Dist: xonsh >=0.12.5
Provides-Extra: dev
Requires-Dist: pytest >=7.0 ; extra == 'dev'
